nimbus_scrapyd_api/__init__.py
nimbus_scrapyd_api/client.py
nimbus_scrapyd_api/compat.py
nimbus_scrapyd_api/constants.py
nimbus_scrapyd_api/exceptions.py
nimbus_scrapyd_api/wrapper.py
nimbus_scrapyd_api-1.0.1.dist-info/LICENSE.md
nimbus_scrapyd_api-1.0.1.dist-info/METADATA
nimbus_scrapyd_api-1.0.1.dist-info/WHEEL
nimbus_scrapyd_api-1.0.1.dist-info/top_level.txt
nimbus_scrapyd_api-1.0.1.dist-info/RECORD
